Metadata-Version: 1.0
Name: distributions-mmmk
Version: 0.1
Summary: Gaussian distributions
Home-page: UNKNOWN
Author: Mica Knox
Author-email: UNKNOWN
License: UNKNOWN
Platform: UNKNOWN
